Workbook

Sheet LEIA-ME
A1: Projeto Financeiro — DELL | Portfólio
A3: PROJETO SIMULADO PARA PORTFÓLIO — não representa trabalho realizado para a Dell Technologies.
A5: Objetivo | B5: Demonstrar organização e análise de rotinas financeiras em Excel, com controle de receitas, despesas, contas e fluxo de caixa.
A6: Ferramentas | B6: Microsoft Excel — nível intermediário
A7: Período simulado | B7: Janeiro de 2026
A8: Estrutura | B8: Cadastro | Receitas | Despesas | Contas | Fluxo de Caixa | Dashboard
A9: Funções aplicadas | B9: SOMASES, CONT.SES, SE, PROCV, SEERRO, SOMA e cálculos percentuais
A10: Status | B10: Concluído para portfólio
A11: Observação | B11: Todos os valores e lançamentos são fictícios e criados exclusivamente para demonstração.

Sheet Cadastro
A1: Cadastro de Categorias e Centros de Custo
A3: Código | B3: Tipo | C3: Categoria | D3: Centro de Custo
A4: REC01 | B4: Receita | C4: Venda de Equipamentos | D4: Comercial
A5: REC02 | B5: Receita | C5: Serviços e Suporte | D5: Serviços
A6: REC03 | B6: Receita | C6: Contratos Corporativos | D6: Corporativo
A7: REC04 | B7: Receita | C7: Outras Receitas | D7: Administrativo
A8: DES01 | B8: Despesa | C8: Fornecedores | D8: Operações
A9: DES02 | B9: Despesa | C9: Folha de Pagamento | D9: Pessoas
A10: DES03 | B10: Despesa | C10: Marketing | D10: Marketing
A11: DES04 | B11: Despesa | C11: Tecnologia e Sistemas | D11: TI
A12: DES05 | B12: Despesa | C12: Logística | D12: Operações
A13: DES06 | B13: Despesa | C13: Administrativo | D13: Administrativo
A14: DES07 | B14: Despesa | C14: Impostos e Taxas | D14: Financeiro

Sheet Receitas
A1: Receitas — Janeiro/2026
A3: Data | B3: Documento | C3: Cliente | D3: Código | E3: Categoria | F3: Centro de Custo | G3: Valor (R$) | H3: Status
A4: 46025 | B4: NF-1001 | C4: Cliente Alpha | D4: REC01 | E4: =IFERROR(VLOOKUP(D4,Cadastro!$A$4:$D$14,3,FALSE),"") -> Venda de Equipamentos | F4: =IFERROR(VLOOKUP(D4,Cadastro!$A$4:$D$14,4,FALSE),"") -> Comercial | G4: 18500 | H4: Recebido
A5: 46028 | B5: NF-1002 | C5: Cliente Beta | D5: REC02 | E5: =IFERROR(VLOOKUP(D5,Cadastro!$A$4:$D$14,3,FALSE),"") -> Serviços e Suporte | F5: =IFERROR(VLOOKUP(D5,Cadastro!$A$4:$D$14,4,FALSE),"") -> Serviços | G5: 9200 | H5: Recebido
A6: 46031 | B6: NF-1003 | C6: Cliente Gama | D6: REC03 | E6: =IFERROR(VLOOKUP(D6,Cadastro!$A$4:$D$14,3,FALSE),"") -> Contratos Corporativos | F6: =IFERROR(VLOOKUP(D6,Cadastro!$A$4:$D$14,4,FALSE),"") -> Corporativo | G6: 27500 | H6: Recebido
A7: 46034 | B7: NF-1004 | C7: Cliente Delta | D7: REC01 | E7: =IFERROR(VLOOKUP(D7,Cadastro!$A$4:$D$14,3,FALSE),"") -> Venda de Equipamentos | F7: =IFERROR(VLOOKUP(D7,Cadastro!$A$4:$D$14,4,FALSE),"") -> Comercial | G7: 14300 | H7: Recebido
A8: 46037 | B8: NF-1005 | C8: Cliente Épsilon | D8: REC02 | E8: =IFERROR(VLOOKUP(D8,Cadastro!$A$4:$D$14,3,FALSE),"") -> Serviços e Suporte | F8: =IFERROR(VLOOKUP(D8,Cadastro!$A$4:$D$14,4,FALSE),"") -> Serviços | G8: 6800 | H8: Recebido
A9: 46041 | B9: NF-1006 | C9: Cliente Zeta | D9: REC01 | E9: =IFERROR(VLOOKUP(D9,Cadastro!$A$4:$D$14,3,FALSE),"") -> Venda de Equipamentos | F9: =IFERROR(VLOOKUP(D9,Cadastro!$A$4:$D$14,4,FALSE),"") -> Comercial | G9: 22100 | H9: Recebido
A10: 46044 | B10: NF-1007 | C10: Cliente Eta | D10: REC03 | E10: =IFERROR(VLOOKUP(D10,Cadastro!$A$4:$D$14,3,FALSE),"") -> Contratos Corporativos | F10: =IFERROR(VLOOKUP(D10,Cadastro!$A$4:$D$14,4,FALSE),"") -> Corporativo | G10: 31200 | H10: Recebido
A11: 46048 | B11: NF-1008 | C11: Cliente Teta | D11: REC04 | E11: =IFERROR(VLOOKUP(D11,Cadastro!$A$4:$D$14,3,FALSE),"") -> Outras Receitas | F11: =IFERROR(VLOOKUP(D11,Cadastro!$A$4:$D$14,4,FALSE),"") -> Administrativo | G11: 4500 | H11: Recebido
A12: 46050 | B12: NF-1009 | C12: Cliente Iota | D12: REC02 | E12: =IFERROR(VLOOKUP(D12,Cadastro!$A$4:$D$14,3,FALSE),"") -> Serviços e Suporte | F12: =IFERROR(VLOOKUP(D12,Cadastro!$A$4:$D$14,4,FALSE),"") -> Serviços | G12: 11800 | H12: Pendente
A13: 46052 | B13: NF-1010 | C13: Cliente Kappa | D13: REC01 | E13: =IFERROR(VLOOKUP(D13,Cadastro!$A$4:$D$14,3,FALSE),"") -> Venda de Equipamentos | F13: =IFERROR(VLOOKUP(D13,Cadastro!$A$4:$D$14,4,FALSE),"") -> Comercial | G13: 16900 | H13: Pendente

Sheet Despesas
A1: Despesas — Janeiro/2026
A3: Data | B3: Documento | C3: Fornecedor | D3: Código | E3: Categoria | F3: Centro de Custo | G3: Valor (R$) | H3: Status
A4: 46026 | B4: DOC-2001 | C4: Fornecedor A | D4: DES01 | E4: =IFERROR(VLOOKUP(D4,Cadastro!$A$4:$D$14,3,FALSE),"") -> Fornecedores | F4: =IFERROR(VLOOKUP(D4,Cadastro!$A$4:$D$14,4,FALSE),"") -> Operações | G4: 12400 | H4: Pago
A5: 46027 | B5: DOC-2002 | C5: Folha Janeiro | D5: DES02 | E5: =IFERROR(VLOOKUP(D5,Cadastro!$A$4:$D$14,3,FALSE),"") -> Folha de Pagamento | F5: =IFERROR(VLOOKUP(D5,Cadastro!$A$4:$D$14,4,FALSE),"") -> Pessoas | G5: 38500 | H5: Pago
A6: 46030 | B6: DOC-2003 | C6: Agência MKT | D6: DES03 | E6: =IFERROR(VLOOKUP(D6,Cadastro!$A$4:$D$14,3,FALSE),"") -> Marketing | F6: =IFERROR(VLOOKUP(D6,Cadastro!$A$4:$D$14,4,FALSE),"") -> Marketing | G6: 6200 | H6: Pago
A7: 46032 | B7: DOC-2004 | C7: Sistemas Cloud | D7: DES04 | E7: =IFERROR(VLOOKUP(D7,Cadastro!$A$4:$D$14,3,FALSE),"") -> Tecnologia e Sistemas | F7: =IFERROR(VLOOKUP(D7,Cadastro!$A$4:$D$14,4,FALSE),"") -> TI | G7: 7800 | H7: Pago
A8: 46035 | B8: DOC-2005 | C8: Transportadora | D8: DES05 | E8: =IFERROR(VLOOKUP(D8,Cadastro!$A$4:$D$14,3,FALSE),"") -> Logística | F8: =IFERROR(VLOOKUP(D8,Cadastro!$A$4:$D$14,4,FALSE),"") -> Operações | G8: 5400 | H8: Pago
A9: 46038 | B9: DOC-2006 | C9: Fornecedor B | D9: DES01 | E9: =IFERROR(VLOOKUP(D9,Cadastro!$A$4:$D$14,3,FALSE),"") -> Fornecedores | F9: =IFERROR(VLOOKUP(D9,Cadastro!$A$4:$D$14,4,FALSE),"") -> Operações | G9: 9600 | H9: Pago
A10: 46042 | B10: DOC-2007 | C10: Escritório e Serviços | D10: DES06 | E10: =IFERROR(VLOOKUP(D10,Cadastro!$A$4:$D$14,3,FALSE),"") -> Administrativo | F10: =IFERROR(VLOOKUP(D10,Cadastro!$A$4:$D$14,4,FALSE),"") -> Administrativo | G10: 3100 | H10: Pago
A11: 46045 | B11: DOC-2008 | C11: Impostos | D11: DES07 | E11: =IFERROR(VLOOKUP(D11,Cadastro!$A$4:$D$14,3,FALSE),"") -> Impostos e Taxas | F11: =IFERROR(VLOOKUP(D11,Cadastro!$A$4:$D$14,4,FALSE),"") -> Financeiro | G11: 11800 | H11: Pago
A12: 46049 | B12: DOC-2009 | C12: Fornecedor C | D12: DES01 | E12: =IFERROR(VLOOKUP(D12,Cadastro!$A$4:$D$14,3,FALSE),"") -> Fornecedores | F12: =IFERROR(VLOOKUP(D12,Cadastro!$A$4:$D$14,4,FALSE),"") -> Operações | G12: 8300 | H12: Pendente
A13: 46051 | B13: DOC-2010 | C13: Sistemas Cloud | D13: DES04 | E13: =IFERROR(VLOOKUP(D13,Cadastro!$A$4:$D$14,3,FALSE),"") -> Tecnologia e Sistemas | F13: =IFERROR(VLOOKUP(D13,Cadastro!$A$4:$D$14,4,FALSE),"") -> TI | G13: 4200 | H13: Pendente

Sheet Contas
A1: Contas a Receber e a Pagar
K2: Data de referência | L2: 46053
A3: Tipo | B3: Documento | C3: Descrição | D3: Vencimento | E3: Valor (R$) | F3: Status | G3: Dias p/ Vencimento | H3: Situação | I3: Prioridade | K3: Critério de alerta (dias) | L3: 7
A4: Receber | B4: NF-1009 | C4: Cliente Iota | D4: 46058 | E4: 11800 | F4: Pendente | G4: =D4-$L$2 -> 5 | H4: =IF(F4<>"Pendente","Concluído",IF(G4<0,"Vencido",IF(G4<=$L$3,"Vence em breve","No prazo"))) -> Vence em breve | I4: =IF(H4="Vencido","Alta",IF(H4="Vence em breve","Média","Normal")) -> Média
A5: Receber | B5: NF-1010 | C5: Cliente Kappa | D5: 46063 | E5: 16900 | F5: Pendente | G5: =D5-$L$2 -> 10 | H5: =IF(F5<>"Pendente","Concluído",IF(G5<0,"Vencido",IF(G5<=$L$3,"Vence em breve","No prazo"))) -> No prazo | I5: =IF(H5="Vencido","Alta",IF(H5="Vence em breve","Média","Normal")) -> Normal
A6: Pagar | B6: DOC-2009 | C6: Fornecedor C | D6: 46056 | E6: 8300 | F6: Pendente | G6: =D6-$L$2 -> 3 | H6: =IF(F6<>"Pendente","Concluído",IF(G6<0,"Vencido",IF(G6<=$L$3,"Vence em breve","No prazo"))) -> Vence em breve | I6: =IF(H6="Vencido","Alta",IF(H6="Vence em breve","Média","Normal")) -> Média
A7: Pagar | B7: DOC-2010 | C7: Sistemas Cloud | D7: 46061 | E7: 4200 | F7: Pendente | G7: =D7-$L$2 -> 8 | H7: =IF(F7<>"Pendente","Concluído",IF(G7<0,"Vencido",IF(G7<=$L$3,"Vence em breve","No prazo"))) -> No prazo | I7: =IF(H7="Vencido","Alta",IF(H7="Vence em breve","Média","Normal")) -> Normal

Sheet Fluxo de Caixa
A1: Fluxo de Caixa Diário — Janeiro/2026
A3: Data | B3: Entradas Recebidas (R$) | C3: Saídas Pagas (R$) | D3: Saldo do Dia (R$) | E3: Saldo Acumulado (R$) | F3: Movimentação
A4: 46023 | B4: =SUMIFS(Receitas!$G$4:$G$13,Receitas!$A$4:$A$13,A4,Receitas!$H$4:$H$13,"Recebido") -> 0 | C4: =SUMIFS(Despesas!$G$4:$G$13,Despesas!$A$4:$A$13,A4,Despesas!$H$4:$H$13,"Pago") -> 0 | D4: =B4-C4 -> 0 | E4: =D4 -> 0 | F4: =IF(D4>0,"Entrada líquida",IF(D4<0,"Saída líquida","Sem movimento")) -> Sem movimento
A5: 46024 | B5: =SUMIFS(Receitas!$G$4:$G$13,Receitas!$A$4:$A$13,A5,Receitas!$H$4:$H$13,"Recebido") -> 0 | C5: =SUMIFS(Despesas!$G$4:$G$13,Despesas!$A$4:$A$13,A5,Despesas!$H$4:$H$13,"Pago") -> 0 | D5: =B5-C5 -> 0 | E5: =E4+D5 -> 0 | F5: =IF(D5>0,"Entrada líquida",IF(D5<0,"Saída líquida","Sem movimento")) -> Sem movimento
A6: 46025 | B6: =SUMIFS(Receitas!$G$4:$G$13,Receitas!$A$4:$A$13,A6,Receitas!$H$4:$H$13,"Recebido") -> 18500 | C6: =SUMIFS(Despesas!$G$4:$G$13,Despesas!$A$4:$A$13,A6,Despesas!$H$4:$H$13,"Pago") -> 0 | D6: =B6-C6 -> 18500 | E6: =E5+D6 -> 18500 | F6: =IF(D6>0,"Entrada líquida",IF(D6<0,"Saída líquida","Sem movimento")) -> Entrada líquida
A7: 46026 | B7: =SUMIFS(Receitas!$G$4:$G$13,Receitas!$A$4:$A$13,A7,Receitas!$H$4:$H$13,"Recebido") -> 0 | C7: =SUMIFS(Despesas!$G$4:$G$13,Despesas!$A$4:$A$13,A7,Despesas!$H$4:$H$13,"Pago") -> 12400 | D7: =B7-C7 -> -12400 | E7: =E6+D7 -> 6100 | F7: =IF(D7>0,"Entrada líquida",IF(D7<0,"Saída líquida","Sem movimento")) -> Saída líquida
A8: 46027 | B8: =SUMIFS(Receitas!$G$4:$G$13,Receitas!$A$4:$A$13,A8,Receitas!$H$4:$H$13,"Recebido") -> 0 | C8: =SUMIFS(Despesas!$G$4:$G$13,Despesas!$A$4:$A$13,A8,Despesas!$H$4:$H$13,"Pago") -> 38500 | D8: =B8-C8 -> -38500 | E8: =E7+D8 -> -32400 | F8: =IF(D8>0,"Entrada líquida",IF(D8<0,"Saída líquida","Sem movimento")) -> Saída líquida
A9: 46028 | B9: =SUMIFS(Receitas!$G$4:$G$13,Receitas!$A$4:$A$13,A9,Receitas!$H$4:$H$13,"Recebido") -> 9200 | C9: =SUMIFS(Despesas!$G$4:$G$13,Despesas!$A$4:$A$13,A9,Despesas!$H$4:$H$13,"Pago") -> 0 | D9: =B9-C9 -> 9200 | E9: =E8+D9 -> -23200 | F9: =IF(D9>0,"Entrada líquida",IF(D9<0,"Saída líquida","Sem movimento")) -> Entrada líquida
A10: 46029 | B10: =SUMIFS(Receitas!$G$4:$G$13,Receitas!$A$4:$A$13,A10,Receitas!$H$4:$H$13,"Recebido") -> 0 | C10: =SUMIFS(Despesas!$G$4:$G$13,Despesas!$A$4:$A$13,A10,Despesas!$H$4:$H$13,"Pago") -> 0 | D10: =B10-C10 -> 0 | E10: =E9+D10 -> -23200 | F10: =IF(D10>0,"Entrada líquida",IF(D10<0,"Saída líquida","Sem movimento")) -> Sem movimento
A11: 46030 | B11: =SUMIFS(Receitas!$G$4:$G$13,Receitas!$A$4:$A$13,A11,Receitas!$H$4:$H$13,"Recebido") -> 0 | C11: =SUMIFS(Despesas!$G$4:$G$13,Despesas!$A$4:$A$13,A11,Despesas!$H$4:$H$13,"Pago") -> 6200 | D11: =B11-C11 -> -6200 | E11: =E10+D11 -> -29400 | F11: =IF(D11>0,"Entrada líquida",IF(D11<0,"Saída líquida","Sem movimento")) -> Saída líquida
A12: 46031 | B12: =SUMIFS(Receitas!$G$4:$G$13,Receitas!$A$4:$A$13,A12,Receitas!$H$4:$H$13,"Recebido") -> 27500 | C12: =SUMIFS(Despesas!$G$4:$G$13,Despesas!$A$4:$A$13,A12,Despesas!$H$4:$H$13,"Pago") -> 0 | D12: =B12-C12 -> 27500 | E12: =E11+D12 -> -1900 | F12: =IF(D12>0,"Entrada líquida",IF(D12<0,"Saída líquida","Sem movimento")) -> Entrada líquida
A13: 46032 | B13: =SUMIFS(Receitas!$G$4:$G$13,Receitas!$A$4:$A$13,A13,Receitas!$H$4:$H$13,"Recebido") -> 0 | C13: =SUMIFS(Despesas!$G$4:$G$13,Despesas!$A$4:$A$13,A13,Despesas!$H$4:$H$13,"Pago") -> 7800 | D13: =B13-C13 -> -7800 | E13: =E12+D13 -> -9700 | F13: =IF(D13>0,"Entrada líquida",IF(D13<0,"Saída líquida","Sem movimento")) -> Saída líquida
A14: 46033 | B14: =SUMIFS(Receitas!$G$4:$G$13,Receitas!$A$4:$A$13,A14,Receitas!$H$4:$H$13,"Recebido") -> 0 | C14: =SUMIFS(Despesas!$G$4:$G$13,Despesas!$A$4:$A$13,A14,Despesas!$H$4:$H$13,"Pago") -> 0 | D14: =B14-C14 -> 0 | E14: =E13+D14 -> -9700 | F14: =IF(D14>0,"Entrada líquida",IF(D14<0,"Saída líquida","Sem movimento")) -> Sem movimento
A15: 46034 | B15: =SUMIFS(Receitas!$G$4:$G$13,Receitas!$A$4:$A$13,A15,Receitas!$H$4:$H$13,"Recebido") -> 14300 | C15: =SUMIFS(Despesas!$G$4:$G$13,Despesas!$A$4:$A$13,A15,Despesas!$H$4:$H$13,"Pago") -> 0 | D15: =B15-C15 -> 14300 | E15: =E14+D15 -> 4600 | F15: =IF(D15>0,"Entrada líquida",IF(D15<0,"Saída líquida","Sem movimento")) -> Entrada líquida
A16: 46035 | B16: =SUMIFS(Receitas!$G$4:$G$13,Receitas!$A$4:$A$13,A16,Receitas!$H$4:$H$13,"Recebido") -> 0 | C16: =SUMIFS(Despesas!$G$4:$G$13,Despesas!$A$4:$A$13,A16,Despesas!$H$4:$H$13,"Pago") -> 5400 | D16: =B16-C16 -> -5400 | E16: =E15+D16 -> -800 | F16: =IF(D16>0,"Entrada líquida",IF(D16<0,"Saída líquida","Sem movimento")) -> Saída líquida
... A34: 46053 | B34: =SUMIFS(Receitas!$G$4:$G$13,Receitas!$A$4:$A$13,A34,Receitas!$H$4:$H$13,"Recebido") -> 0 | C34: =SUMIFS(Despesas!$G$4:$G$13,Despesas!$A$4:$A$13,A34,Despesas!$H$4:$H$13,"Pago") -> 0 | D34: =B34-C34 -> 0 | E34: =E33+D34 -> 39300 | F34: =IF(D34>0,"Entrada líquida",IF(D34<0,"Saída líquida","Sem movimento")) -> Sem movimento

Sheet Dashboard
A1: Dashboard Financeiro — Janeiro/2026
A3: Visão gerencial do projeto simulado para portfólio
A5: Receitas Totais | B5: =SUM(Receitas!G4:G13) -> 162800 | D5: Receitas Recebidas | E5: =SUMIFS(Receitas!G4:G13,Receitas!H4:H13,"Recebido") -> 134100 | G5: Despesas Totais | H5: =SUM(Despesas!G4:G13) -> 107300 | J5: Despesas Pagas | K5: =SUMIFS(Despesas!G4:G13,Despesas!H4:H13,"Pago") -> 94800
A8: Resultado Previsto | B8: =B5-H5 -> 55500 | D8: Resultado Realizado | E8: =E5-K5 -> 39300 | G8: Margem Realizada | H8: =IFERROR(E8/E5,0) -> 0.29306488 | J8: Saldo a Receber | K8: =SUMIFS(Receitas!G4:G13,Receitas!H4:H13,"Pendente") -> 28700
A11: Saldo a Pagar | B11: =SUMIFS(Despesas!G4:G13,Despesas!H4:H13,"Pendente") -> 12500 | D11: Qtd. Receitas | E11: =COUNTIFS(Receitas!A4:A13,">0") -> 10 | G11: Qtd. Despesas | H11: =COUNTIFS(Despesas!A4:A13,">0") -> 10 | J11: Saldo Final Caixa | K11: ='Fluxo de Caixa'!E34 -> 39300
A15: Receitas por Categoria | B15: Valor (R$) | D15: Despesas por Categoria | E15: Valor (R$)
A16: Venda de Equipamentos | B16: =SUMIFS(Receitas!$G$4:$G$13,Receitas!$E$4:$E$13,A16) -> 71800 | D16: Fornecedores | E16: =SUMIFS(Despesas!$G$4:$G$13,Despesas!$E$4:$E$13,D16) -> 30300
A17: Serviços e Suporte | B17: =SUMIFS(Receitas!$G$4:$G$13,Receitas!$E$4:$E$13,A17) -> 27800 | D17: Folha de Pagamento | E17: =SUMIFS(Despesas!$G$4:$G$13,Despesas!$E$4:$E$13,D17) -> 38500
A18: Contratos Corporativos | B18: =SUMIFS(Receitas!$G$4:$G$13,Receitas!$E$4:$E$13,A18) -> 58700 | D18: Marketing | E18: =SUMIFS(Despesas!$G$4:$G$13,Despesas!$E$4:$E$13,D18) -> 6200
A19: Outras Receitas | B19: =SUMIFS(Receitas!$G$4:$G$13,Receitas!$E$4:$E$13,A19) -> 4500 | D19: Tecnologia e Sistemas | E19: =SUMIFS(Despesas!$G$4:$G$13,Despesas!$E$4:$E$13,D19) -> 12000
D20: Logística | E20: =SUMIFS(Despesas!$G$4:$G$13,Despesas!$E$4:$E$13,D20) -> 5400
D21: Administrativo | E21: =SUMIFS(Despesas!$G$4:$G$13,Despesas!$E$4:$E$13,D21) -> 3100
D22: Impostos e Taxas | E22: =SUMIFS(Despesas!$G$4:$G$13,Despesas!$E$4:$E$13,D22) -> 11800
A24: Indicador | B24: Valor (R$)
A25: Receitas Recebidas | B25: =E5 -> 134100
A26: Despesas Pagas | B26: =K5 -> 94800
A27: Resultado Realizado | B27: =E8 -> 39300

Sheet Fórmulas
A1: Fórmulas e Funções Aplicadas
A3: Função | B3: Aplicação no projeto | C3: Exemplo | D3: Nível demonstrado
A4: PROCV + SEERRO | B4: Buscar categoria e centro de custo pelo código | C4: =SEERRO(PROCV(D4;Cadastro!$A$4:$D$14;3;FALSO);"") | D4: Intermediário
A5: SOMASES | B5: Somar valores por data, status ou categoria | C5: =SOMASES(Receitas!$G$4:$G$13;Receitas!$H$4:$H$13;"Recebido") | D5: Intermediário
A6: CONT.SES | B6: Contar registros conforme critérios | C6: =CONT.SES(Receitas!A4:A13;">0") | D6: Intermediário
A7: SE | B7: Classificar vencimentos e movimentações | C7: =SE(G4<0;"Vencido";"No prazo") | D7: Intermediário
A8: SOMA | B8: Totalizar receitas e despesas | C8: =SOMA(Receitas!G4:G13) | D8: Básico/Intermediário
A9: SEERRO | B9: Evitar erros visíveis nas buscas | C9: =SEERRO(PROCV(...);"") | D9: Intermediário
A10: Cálculo percentual | B10: Calcular margem realizada | C10: =SEERRO(Resultado/Receita;0) | D10: Intermediário
